mahdix/__init__.py
mahdix/mat.py
mahdix-0.1.5.1.dist-info/METADATA
mahdix-0.1.5.1.dist-info/WHEEL
mahdix-0.1.5.1.dist-info/top_level.txt
mahdix-0.1.5.1.dist-info/RECORD
