Metadata-Version: 2.1
Name: mahdix
Version: 0.1.5.1
Summary: this is a simple pip modul and test
